aimq/__init__.py
aimq/__main__.py
aimq/attachment.py
aimq/config.py
aimq/helpers.py
aimq/job.py
aimq/logger.py
aimq/py.typed
aimq/queue.py
aimq/utils.py
aimq/worker.py
aimq/clients/__init__.py
aimq/clients/mistral.py
aimq/clients/supabase.py
aimq/commands/__init__.py
aimq/commands/disable.py
aimq/commands/enable.py
aimq/commands/init.py
aimq/commands/send.py
aimq/commands/start.py
aimq/commands/shared/__init__.py
aimq/commands/shared/config.py
aimq/commands/shared/git_loader.py
aimq/commands/shared/migration.py
aimq/commands/shared/paths.py
aimq/commands/shared/templates/__init__.py
aimq/commands/shared/templates/config.toml
aimq/commands/shared/templates/create_queue.sql
aimq/commands/shared/templates/env
aimq/commands/shared/templates/env.example.template
aimq/commands/shared/templates/setup_aimq.sql
aimq/commands/shared/templates/tasks.py
aimq/commands/shared/templates/docker/.dockerignore.template
aimq/commands/shared/templates/docker/Dockerfile.template
aimq/commands/shared/templates/docker/__init__.py
aimq/commands/shared/templates/docker/docker-compose.yml.template
aimq/providers/__init__.py
aimq/providers/base.py
aimq/providers/supabase.py
aimq/tools/__init__.py
aimq/tools/mistral/__init__.py
aimq/tools/mistral/document_ocr.py
aimq/tools/mistral/upload_file.py
aimq/tools/ocr/__init__.py
aimq/tools/ocr/image_ocr.py
aimq/tools/ocr/processor.py
aimq/tools/pdf/__init__.py
aimq/tools/pdf/page_splitter.py
aimq/tools/supabase/__init__.py
aimq/tools/supabase/enqueue.py
aimq/tools/supabase/get_url.py
aimq/tools/supabase/read_file.py
aimq/tools/supabase/read_record.py
aimq/tools/supabase/write_file.py
aimq/tools/supabase/write_record.py
aimq-0.1.2.dist-info/METADATA
aimq-0.1.2.dist-info/WHEEL
aimq-0.1.2.dist-info/entry_points.txt
aimq-0.1.2.dist-info/licenses/LICENSE
aimq-0.1.2.dist-info/RECORD
