Metadata-Version: 2.4
Name: aimq
Version: 0.1.2
Summary: A robust message queue processor for Supabase pgmq with AI-powered document processing capabilities
Project-URL: Homepage, https://github.com/bldxio/aimq
Project-URL: Repository, https://github.com/bldxio/aimq
Project-URL: Documentation, https://bldxio.github.io/aimq
Author: AIMQ Contributors
License: MIT
License-File: LICENSE
Keywords: ai,document-processing,machine-learning,ocr,pgmq,queue,supabase
Classifier: Development Status :: 4 - Beta
Classifier: Intended Audience :: Developers
Classifier: License :: OSI Approved :: MIT License
Classifier: Programming Language :: Python :: 3
Classifier: Programming Language :: Python :: 3.11
Classifier: Programming Language :: Python :: 3.12
Classifier: Topic :: Scientific/Engineering :: Artificial Intelligence
Classifier: Topic :: Software Development :: Libraries :: Python Modules
Requires-Python: <=3.13,>=3.11
Requires-Dist: easyocr<2.0.0,>=1.7.1
Requires-Dist: filetype<2.0.0,>=1.2.0
Requires-Dist: humanize<5.0.0,>=4.11.0
Requires-Dist: langchain-mistralai<0.3.0,>=0.2.11
Requires-Dist: langchain-openai<0.3.0,>=0.2.12
Requires-Dist: langchain-text-splitters<1.0.0,>=0.3.9
Requires-Dist: langchain<0.4.0,>=0.3.10
Requires-Dist: mistralai<2.0.0,>=1.9.10
Requires-Dist: mkdocs-dracula-theme<2.0.0,>=1.0.7
Requires-Dist: openai<2.0.0,>=1.57.1
Requires-Dist: pillow<13.0.0,>=10.2.0
Requires-Dist: pydantic-settings<3.0.0,>=2.6.1
Requires-Dist: pypdfium2<5.0.0,>=4.30.0
Requires-Dist: python-dotenv<2.0.0,>=1.0.0
Requires-Dist: rich<15.0.0,>=13.7.0
Requires-Dist: supabase<3.0.0,>=2.10.0
Requires-Dist: tomlkit<1.0.0,>=0.13.2
Requires-Dist: torch<3.0.0,>=2.9.0
Requires-Dist: typer<1.0.0,>=0.9.0
